{"data":{"allReposYaml":{"edges":[{"node":{"badges":[{"badge":"react-first"}],"description":"A compact, modern, and well documented library targeting the needs of 3D graphics.","id":"7739cefb-f00c-5c12-8243-349ad83a389b","img":null,"name":"math.gl","page":"https://uber-web.github.io/math.gl/#/","type":"MODULE","url":"uber-web/math.gl"}},{"node":{"badges":[{"badge":"javascript"}],"description":"Management of browser events and gestures in a portable, modern way.","id":"MDEwOlJlcG9zaXRvcnkxMDQ1MDMyMjA=","img":null,"name":"mjolnir.js","page":"https://uber-web.github.io/mjolnir.js/#/","type":"MODULE","url":"uber-web/mjolnir.js"}},{"node":{"badges":[{"badge":"javascript"}],"description":"A library that collects 3D enabled web mercator projection math and tests.","id":"a0c55b1f-ab6e-52c7-a746-883aacf4366d","img":null,"name":"viewport-mercator-project","page":"https://uber-common.github.io/viewport-mercator-project/#/","type":"MODULE","url":"uber-common/viewport-mercator-project"}},{"node":{"badges":[{"badge":"javascript"}],"description":"JavaScript console instrumentation and benchmarking for browser and node.js","id":"900bc578-7908-52d8-ab9c-556616a2d993","img":null,"name":"probe.gl","page":"https://uber-web.github.io/probe.gl/#/","type":"MODULE","url":"uber-web/probe.gl"}},{"node":{"badges":[{"badge":"c"},{"badge":"javascript"}],"description":"A hexagonal hierarchical geospatial indexing system","id":"2a25467d-b70c-5001-ac4a-7209e5fdcd4d","img":null,"name":"h3","page":"https://uber.github.io/h3/#/","type":"MODULE","url":"uber/h3"}},{"node":{"badges":[{"badge":"javascript"}],"description":"A suite of 3D-enabled data editing overlays, suitable for deck.gl","id":"27d62f33-18d9-5af1-ad41-75e5526507f4","img":null,"name":"nebula.gl","page":"https://neb.gl/#/","type":"MODULE","url":"uber/nebula.gl"}},{"node":{"badges":[{"badge":"javascript"}],"description":"A suite of framework-independent loaders (i.e. parsers) for 3D geometries and assets, as well as geospatial formats.","id":"ce910d54-a139-5cb8-9d2a-b2fa1f47c5b5","img":null,"name":"loaders.gl","page":"https://uber-web.github.io/loaders.gl/#/","type":"MODULE","url":"uber-web/loaders.gl"}}]}}}